sonimei/__const__.py
sonimei/__init__.py
sonimei/_sonimei.py
sonimei/app.py
sonimei/icfg.py
sonimei/metas.py
sonimei/site_header.py
sonimei/sites.py
sonimei/wget.py
sonimei/zutil.py
tests/__init__.py
sonimei-0.1.8.1.dist-info/LICENSE
sonimei-0.1.8.1.dist-info/METADATA
sonimei-0.1.8.1.dist-info/WHEEL
sonimei-0.1.8.1.dist-info/entry_points.txt
sonimei-0.1.8.1.dist-info/top_level.txt
sonimei-0.1.8.1.dist-info/RECORD
