Metadata-Version: 2.1
Name: sonimei
Version: 0.1.8.1
Summary: music downloader of music.sonimei.cn
Home-page: https://github.com/coghost/Sonimei-Music
Author: lihe
Author-email: imanux@sina.com
License: GPL
Project-URL: Bug Reports, https://github.com/coghost/Sonimei-Music/issues
Project-URL: Source, https://github.com/coghost/Sonimei-Music
Keywords: sonimei,music downloader
Platform: UNKNOWN
Classifier: Programming Language :: Python :: 3.7
Requires-Python: >=3.7
Requires-Dist: wget
Requires-Dist: izen
Requires-Dist: click
Requires-Dist: logzero
Requires-Dist: mutagen
Requires-Dist: lxml
Requires-Dist: requests
Requires-Dist: selenium
Requires-Dist: PyYAML
